CHANGELOG.txt
LICENCE.txt
MANIFEST.in
README.txt
setup.py
CybrocksLibrary/__init__.py
CybrocksLibrary.egg-info/PKG-INFO
CybrocksLibrary.egg-info/SOURCES.txt
CybrocksLibrary.egg-info/dependency_links.txt
CybrocksLibrary.egg-info/top_level.txt