Metadata-Version: 2.1
Name: CybrocksLibrary
Version: 0.0.1.2
Summary: just some reandom crap
Home-page: 
Author: Cybrock9000
Author-email: ethandepree672@gmail.com
License: MIT
Keywords: Library
Classifier: Development Status :: 5 - Production/Stable
Classifier: Intended Audience :: Education
Classifier: Operating System :: Microsoft :: Windows :: Windows 11
Classifier: License :: OSI Approved :: MIT License
Classifier: Programming Language :: Python :: 3
License-File: LICENCE.txt
